Metadata-Version: 2.4
Name: pluto-ml
Version: 0.0.4
Summary: Pluto ML - Machine Learning Operations Framework
License-File: LICENSE
Author: jqssun
Requires-Python: >=3.10,<4.0
Classifier: Programming Language :: Python :: 3
Classifier: Programming Language :: Python :: 3.10
Classifier: Programming Language :: Python :: 3.11
Classifier: Programming Language :: Python :: 3.12
Classifier: Programming Language :: Python :: 3.13
Classifier: Programming Language :: Python :: 3.14
Provides-Extra: full
Requires-Dist: GitPython (>=3.1)
Requires-Dist: httpx[http2] (>=0.24)
Requires-Dist: keyring (>=24.0)
Requires-Dist: keyrings-alt (>=5.0)
Requires-Dist: numpy (>=2.0,<3.0)
Requires-Dist: nvidia-ml-py (>=11.515.0) ; extra == "full"
Requires-Dist: pillow (>=10.0)
Requires-Dist: psutil (>=5.9)
Requires-Dist: rich (>=13.0)
Requires-Dist: soundfile (>=0.12)
